[
  {
      "sido": "부산광역시",
      "source_main": "비산업 연소",
      "CO": 1645.56,
      "NOx": 4717.76,
      "SOx": 226.79,
      "TSP": 51.51,
      "PM10": 48.76,
      "PM2P5": 40.01,
      "VOC": 171.67,
      "NH3": 71.46,
      "BC": 11.1,
      "key": "부산광역시_비산업 연소"
  },
  {
      "sido": "부산광역시",
      "source_main": "제조업 연소",
      "CO": 518.1,
      "NOx": 1612.42,
      "SOx": 327.51,
      "TSP": 202.47,
      "PM10": 120.31,
      "PM2P5": 49.4,
      "VOC": 66.88,
      "NH3": 23.64,
      "BC": 3.7,
      "key": "부산광역시_제조업 연소"
  },
  {
      "sido": "부산광역시",
      "source_main": "생산공정",
      "CO": 0,
      "NOx": 382.52,
      "SOx": 669.37,
      "TSP": 16.42,
      "PM10": 11.77,
      "PM2P5": 8.46,
      "VOC": 222.91,
      "NH3": 16.98,
      "BC": 0.03,
      "key": "부산광역시_생산공정"
  },
  {
      "sido": "부산광역시",
      "source_main": "에너지수송 및 저장",
      "CO": 0,
      "NOx": 0,
      "SOx": 0,
      "TSP": 0,
      "PM10": 0,
      "PM2P5": 0,
      "VOC": 587.88,
      "NH3": 0,
      "BC": 0,
      "key": "부산광역시_에너지수송 및 저장"
  },
  {
      "sido": "부산광역시",
      "source_main": "유기용제 사용",
      "CO": 0,
      "NOx": 0,
      "SOx": 0,
      "TSP": 0,
      "PM10": 0,
      "PM2P5": 0,
      "VOC": 25274.87,
      "NH3": 0,
      "BC": 0,
      "key": "부산광역시_유기용제 사용"
  },
  {
      "sido": "부산광역시",
      "source_main": "도로이동오염원",
      "CO": 7548.67,
      "NOx": 11753.5,
      "SOx": 10.37,
      "TSP": 149.66,
      "PM10": 149.66,
      "PM2P5": 137.68,
      "VOC": 1799.32,
      "NH3": 91.64,
      "BC": 71.37,
      "key": "부산광역시_도로이동오염원"
  },
  {
      "sido": "부산광역시",
      "source_main": "비도로이동오염원",
      "CO": 9381.24,
      "NOx": 23005.69,
      "SOx": 2028.22,
      "TSP": 1383.57,
      "PM10": 1383.32,
      "PM2P5": 1270.39,
      "VOC": 3687.62,
      "NH3": 4.03,
      "BC": 309.36,
      "key": "부산광역시_비도로이동오염원"
  },
  {
      "sido": "부산광역시",
      "source_main": "폐기물처리",
      "CO": 45.06,
      "NOx": 179.61,
      "SOx": 28.39,
      "TSP": 5.99,
      "PM10": 4.4,
      "PM2P5": 3.8,
      "VOC": 1095.01,
      "NH3": 1.23,
      "BC": 0.06,
      "key": "부산광역시_폐기물처리"
  },
  {
      "sido": "부산광역시",
      "source_main": "농업",
      "CO": 0,
      "NOx": 0,
      "SOx": 0,
      "TSP": 0,
      "PM10": 0,
      "PM2P5": 0,
      "VOC": 0,
      "NH3": 164.08,
      "BC": 0,
      "key": "부산광역시_농업"
  },
  {
      "sido": "부산광역시",
      "source_main": "기타 면오염원",
      "CO": 372.39,
      "NOx": 8.77,
      "SOx": 0,
      "TSP": 24.09,
      "PM10": 15.3,
      "PM2P5": 13.77,
      "VOC": 30.87,
      "NH3": 847.99,
      "BC": 0.61,
      "key": "부산광역시_기타 면오염원"
  },
  {
      "sido": "부산광역시",
      "source_main": "비산먼지",
      "CO": 0,
      "NOx": 0,
      "SOx": 0,
      "TSP": 14701.19,
      "PM10": 4752.87,
      "PM2P5": 779.13,
      "VOC": 0,
      "NH3": 0,
      "BC": 3.25,
      "key": "부산광역시_비산먼지"
  },
  {
      "sido": "부산광역시",
      "source_main": "생물성 연소",
      "CO": 825.72,
      "NOx": 21.63,
      "SOx": 0.7,
      "TSP": 136.9,
      "PM10": 95.74,
      "PM2P5": 82.18,
      "VOC": 258.37,
      "NH3": 0.09,
      "BC": 7.92,
      "key": "부산광역시_생물성 연소"
  },
  {
      "sido": "부산광역시",
      "source_main": "에너지산업 연소",
      "CO": 1873.74,
      "NOx": 1417.32,
      "SOx": 189.34,
      "TSP": 53.89,
      "PM10": 53.55,
      "PM2P5": 51.07,
      "VOC": 251.58,
      "NH3": 240.45,
      "BC": 16.49,
      "key": "부산광역시_에너지산업 연소"
  },
  {
      "sido": "대구광역시",
      "source_main": "비산업 연소",
      "CO": 1748,
      "NOx": 3453.86,
      "SOx": 244.4,
      "TSP": 38.94,
      "PM10": 35.33,
      "PM2P5": 27.45,
      "VOC": 127.75,
      "NH3": 129.16,
      "BC": 7.7,
      "key": "대구광역시_비산업 연소"
  },
  {
      "sido": "대구광역시",
      "source_main": "제조업 연소",
      "CO": 264.58,
      "NOx": 1492.01,
      "SOx": 1508.53,
      "TSP": 837.88,
      "PM10": 488.95,
      "PM2P5": 172.04,
      "VOC": 35.28,
      "NH3": 9.74,
      "BC": 4.07,
      "key": "대구광역시_제조업 연소"
  },
  {
      "sido": "대구광역시",
      "source_main": "생산공정",
      "CO": 0,
      "NOx": 0.02,
      "SOx": 0.01,
      "TSP": 0.33,
      "PM10": 0.2,
      "PM2P5": 0.12,
      "VOC": 5002.29,
      "NH3": 107.25,
      "BC": 0,
      "key": "대구광역시_생산공정"
  },
  {
      "sido": "대구광역시",
      "source_main": "에너지수송 및 저장",
      "CO": 0,
      "NOx": 0,
      "SOx": 0,
      "TSP": 0,
      "PM10": 0,
      "PM2P5": 0,
      "VOC": 544.66,
      "NH3": 0,
      "BC": 0,
      "key": "대구광역시_에너지수송 및 저장"
  },
  {
      "sido": "대구광역시",
      "source_main": "유기용제 사용",
      "CO": 0,
      "NOx": 0,
      "SOx": 0,
      "TSP": 0,
      "PM10": 0,
      "PM2P5": 0,
      "VOC": 20547.29,
      "NH3": 0,
      "BC": 0,
      "key": "대구광역시_유기용제 사용"
  },
  {
      "sido": "대구광역시",
      "source_main": "도로이동오염원",
      "CO": 6921.7,
      "NOx": 12037.2,
      "SOx": 9.56,
      "TSP": 151.86,
      "PM10": 151.86,
      "PM2P5": 139.71,
      "VOC": 1544.32,
      "NH3": 81.85,
      "BC": 75.07,
      "key": "대구광역시_도로이동오염원"
  },
  {
      "sido": "대구광역시",
      "source_main": "비도로이동오염원",
      "CO": 1727.06,
      "NOx": 3515.84,
      "SOx": 15.26,
      "TSP": 193.3,
      "PM10": 193.24,
      "PM2P5": 177.78,
      "VOC": 451.58,
      "NH3": 1.89,
      "BC": 137.11,
      "key": "대구광역시_비도로이동오염원"
  },
  {
      "sido": "대구광역시",
      "source_main": "폐기물처리",
      "CO": 178.88,
      "NOx": 178.42,
      "SOx": 32.58,
      "TSP": 10.88,
      "PM10": 7.88,
      "PM2P5": 6.84,
      "VOC": 997.8,
      "NH3": 1.18,
      "BC": 0.1,
      "key": "대구광역시_폐기물처리"
  },
  {
      "sido": "대구광역시",
      "source_main": "농업",
      "CO": 0,
      "NOx": 0,
      "SOx": 0,
      "TSP": 0,
      "PM10": 0,
      "PM2P5": 0,
      "VOC": 0,
      "NH3": 496.14,
      "BC": 0,
      "key": "대구광역시_농업"
  },
  {
      "sido": "대구광역시",
      "source_main": "기타 면오염원",
      "CO": 184.05,
      "NOx": 4.34,
      "SOx": 0,
      "TSP": 11.92,
      "PM10": 7.58,
      "PM2P5": 6.82,
      "VOC": 15.29,
      "NH3": 604.59,
      "BC": 0.3,
      "key": "대구광역시_기타 면오염원"
  },
  {
      "sido": "대구광역시",
      "source_main": "비산먼지",
      "CO": 0,
      "NOx": 0,
      "SOx": 0,
      "TSP": 7253.25,
      "PM10": 2009.14,
      "PM2P5": 367.92,
      "VOC": 0,
      "NH3": 0,
      "BC": 2.91,
      "key": "대구광역시_비산먼지"
  },
  {
      "sido": "대구광역시",
      "source_main": "생물성 연소",
      "CO": 1816.67,
      "NOx": 57.09,
      "SOx": 1.21,
      "TSP": 238.26,
      "PM10": 133.4,
      "PM2P5": 108.99,
      "VOC": 616.26,
      "NH3": 0.21,
      "BC": 13.86,
      "key": "대구광역시_생물성 연소"
  },
  {
      "sido": "대구광역시",
      "source_main": "에너지산업 연소",
      "CO": 694.25,
      "NOx": 605.55,
      "SOx": 159.44,
      "TSP": 36.32,
      "PM10": 35.04,
      "PM2P5": 30.34,
      "VOC": 97.76,
      "NH3": 25.8,
      "BC": 5.54,
      "key": "대구광역시_에너지산업 연소"
  },
  {
      "sido": "울산광역시",
      "source_main": "비산업 연소",
      "CO": 628.8,
      "NOx": 2000.02,
      "SOx": 105.81,
      "TSP": 28.07,
      "PM10": 26.34,
      "PM2P5": 19.92,
      "VOC": 72.3,
      "NH3": 34.31,
      "BC": 4.72,
      "key": "울산광역시_비산업 연소"
  },
  {
      "sido": "울산광역시",
      "source_main": "제조업 연소",
      "CO": 3304.15,
      "NOx": 16827.24,
      "SOx": 2696.45,
      "TSP": 792.52,
      "PM10": 490.7,
      "PM2P5": 230.86,
      "VOC": 487.96,
      "NH3": 133.53,
      "BC": 33.11,
      "key": "울산광역시_제조업 연소"
  },
  {
      "sido": "울산광역시",
      "source_main": "생산공정",
      "CO": 12684.51,
      "NOx": 1723.67,
      "SOx": 31675.44,
      "TSP": 1508.97,
      "PM10": 721.4,
      "PM2P5": 597.31,
      "VOC": 51647.85,
      "NH3": 11750.79,
      "BC": 0.05,
      "key": "울산광역시_생산공정"
  },
  {
      "sido": "울산광역시",
      "source_main": "에너지수송 및 저장",
      "CO": 0,
      "NOx": 0,
      "SOx": 0,
      "TSP": 0,
      "PM10": 0,
      "PM2P5": 0,
      "VOC": 3168.25,
      "NH3": 0,
      "BC": 0,
      "key": "울산광역시_에너지수송 및 저장"
  },
  {
      "sido": "울산광역시",
      "source_main": "유기용제 사용",
      "CO": 0,
      "NOx": 0,
      "SOx": 0,
      "TSP": 0,
      "PM10": 0,
      "PM2P5": 0,
      "VOC": 17981.68,
      "NH3": 0,
      "BC": 0,
      "key": "울산광역시_유기용제 사용"
  },
  {
      "sido": "울산광역시",
      "source_main": "도로이동오염원",
      "CO": 3528.79,
      "NOx": 6126.91,
      "SOx": 5.09,
      "TSP": 81.91,
      "PM10": 81.91,
      "PM2P5": 75.36,
      "VOC": 728.57,
      "NH3": 44.85,
      "BC": 43.41,
      "key": "울산광역시_도로이동오염원"
  },
  {
      "sido": "울산광역시",
      "source_main": "비도로이동오염원",
      "CO": 1503.55,
      "NOx": 9718.13,
      "SOx": 955.61,
      "TSP": 545.32,
      "PM10": 545.3,
      "PM2P5": 495.71,
      "VOC": 479.68,
      "NH3": 1.93,
      "BC": 119.94,
      "key": "울산광역시_비도로이동오염원"
  },
  {
      "sido": "울산광역시",
      "source_main": "폐기물처리",
      "CO": 217.88,
      "NOx": 2562.53,
      "SOx": 206,
      "TSP": 68.65,
      "PM10": 52.73,
      "PM2P5": 42.3,
      "VOC": 6630.76,
      "NH3": 1.13,
      "BC": 0.64,
      "key": "울산광역시_폐기물처리"
  },
  {
      "sido": "울산광역시",
      "source_main": "농업",
      "CO": 0,
      "NOx": 0,
      "SOx": 0,
      "TSP": 0,
      "PM10": 0,
      "PM2P5": 0,
      "VOC": 0,
      "NH3": 1045.89,
      "BC": 0,
      "key": "울산광역시_농업"
  },
  {
      "sido": "울산광역시",
      "source_main": "기타 면오염원",
      "CO": 884.49,
      "NOx": 24.44,
      "SOx": 0,
      "TSP": 100.12,
      "PM10": 63.47,
      "PM2P5": 57.12,
      "VOC": 139.77,
      "NH3": 284,
      "BC": 5.17,
      "key": "울산광역시_기타 면오염원"
  },
  {
      "sido": "울산광역시",
      "source_main": "비산먼지",
      "CO": 0,
      "NOx": 0,
      "SOx": 0,
      "TSP": 3932.91,
      "PM10": 1039.79,
      "PM2P5": 197.17,
      "VOC": 0,
      "NH3": 0,
      "BC": 1.75,
      "key": "울산광역시_비산먼지"
  },
  {
      "sido": "울산광역시",
      "source_main": "생물성 연소",
      "CO": 1593.62,
      "NOx": 45.02,
      "SOx": 0.78,
      "TSP": 190.25,
      "PM10": 98.51,
      "PM2P5": 80.1,
      "VOC": 463.95,
      "NH3": 0.14,
      "BC": 13.73,
      "key": "울산광역시_생물성 연소"
  },
  {
      "sido": "울산광역시",
      "source_main": "에너지산업 연소",
      "CO": 3160.82,
      "NOx": 3586.95,
      "SOx": 1323.7,
      "TSP": 100.83,
      "PM10": 92.65,
      "PM2P5": 82.81,
      "VOC": 444.72,
      "NH3": 272.03,
      "BC": 27.51,
      "key": "울산광역시_에너지산업 연소"
  },
  {
      "sido": "경상북도",
      "source_main": "비산업 연소",
      "CO": 1508.7,
      "NOx": 2787.34,
      "SOx": 302.16,
      "TSP": 41.45,
      "PM10": 36.84,
      "PM2P5": 28.22,
      "VOC": 99.41,
      "NH3": 131.59,
      "BC": 6.3,
      "key": "경상북도_비산업 연소"
  },
  {
      "sido": "경상북도",
      "source_main": "제조업 연소",
      "CO": 1944.85,
      "NOx": 10363.96,
      "SOx": 3499.14,
      "TSP": 2813.06,
      "PM10": 1646.85,
      "PM2P5": 731.09,
      "VOC": 315.57,
      "NH3": 73.23,
      "BC": 20.94,
      "key": "경상북도_제조업 연소"
  },
  {
      "sido": "경상북도",
      "source_main": "생산공정",
      "CO": 1873.48,
      "NOx": 14586.54,
      "SOx": 9681.6,
      "TSP": 2735.24,
      "PM10": 1677.92,
      "PM2P5": 1298.1,
      "VOC": 6028,
      "NH3": 574.26,
      "BC": 3.36,
      "key": "경상북도_생산공정"
  },
  {
      "sido": "경상북도",
      "source_main": "에너지수송 및 저장",
      "CO": 0,
      "NOx": 0,
      "SOx": 0,
      "TSP": 0,
      "PM10": 0,
      "PM2P5": 0,
      "VOC": 1006.06,
      "NH3": 0,
      "BC": 0,
      "key": "경상북도_에너지수송 및 저장"
  },
  {
      "sido": "경상북도",
      "source_main": "유기용제 사용",
      "CO": 0,
      "NOx": 0,
      "SOx": 0,
      "TSP": 0,
      "PM10": 0,
      "PM2P5": 0,
      "VOC": 20232.51,
      "NH3": 0,
      "BC": 0,
      "key": "경상북도_유기용제 사용"
  },
  {
      "sido": "경상북도",
      "source_main": "도로이동오염원",
      "CO": 6409.24,
      "NOx": 14978.48,
      "SOx": 10.78,
      "TSP": 224.05,
      "PM10": 224.05,
      "PM2P5": 206.13,
      "VOC": 1029.79,
      "NH3": 89.93,
      "BC": 126.15,
      "key": "경상북도_도로이동오염원"
  },
  {
      "sido": "경상북도",
      "source_main": "비도로이동오염원",
      "CO": 7175.35,
      "NOx": 6440.81,
      "SOx": 359.42,
      "TSP": 514.8,
      "PM10": 514.8,
      "PM2P5": 482.72,
      "VOC": 3077.22,
      "NH3": 5.26,
      "BC": 206.93,
      "key": "경상북도_비도로이동오염원"
  },
  {
      "sido": "경상북도",
      "source_main": "폐기물처리",
      "CO": 114.6,
      "NOx": 576.61,
      "SOx": 96.42,
      "TSP": 16.96,
      "PM10": 12.28,
      "PM2P5": 10.77,
      "VOC": 3507.4,
      "NH3": 1.28,
      "BC": 0.16,
      "key": "경상북도_폐기물처리"
  },
  {
      "sido": "경상북도",
      "source_main": "농업",
      "CO": 0,
      "NOx": 0,
      "SOx": 0,
      "TSP": 0,
      "PM10": 0,
      "PM2P5": 0,
      "VOC": 0,
      "NH3": 9443.33,
      "BC": 0,
      "key": "경상북도_농업"
  },
  {
      "sido": "경상북도",
      "source_main": "기타 면오염원",
      "CO": 209.78,
      "NOx": 4.98,
      "SOx": 0,
      "TSP": 14.04,
      "PM10": 8.92,
      "PM2P5": 8.03,
      "VOC": 18.12,
      "NH3": 413.31,
      "BC": 0.38,
      "key": "경상북도_기타 면오염원"
  },
  {
      "sido": "경상북도",
      "source_main": "비산먼지",
      "CO": 0,
      "NOx": 0,
      "SOx": 0,
      "TSP": 13257.43,
      "PM10": 3987.11,
      "PM2P5": 698.45,
      "VOC": 0,
      "NH3": 0,
      "BC": 6.35,
      "key": "경상북도_비산먼지"
  },
  {
      "sido": "경상북도",
      "source_main": "생물성 연소",
      "CO": 12094.56,
      "NOx": 518.83,
      "SOx": 3.33,
      "TSP": 1487.2,
      "PM10": 692.28,
      "PM2P5": 561.68,
      "VOC": 5065.76,
      "NH3": 0.8,
      "BC": 116.09,
      "key": "경상북도_생물성 연소"
  },
  {
      "sido": "경상북도",
      "source_main": "에너지산업 연소",
      "CO": 137.23,
      "NOx": 611.19,
      "SOx": 213.76,
      "TSP": 8.23,
      "PM10": 4.69,
      "PM2P5": 3.77,
      "VOC": 17.38,
      "NH3": 1.99,
      "BC": 0.09,
      "key": "경상북도_에너지산업 연소"
  },
  {
      "sido": "경상남도",
      "source_main": "비산업 연소",
      "CO": 1199.32,
      "NOx": 3423.1,
      "SOx": 206.91,
      "TSP": 52.31,
      "PM10": 48.73,
      "PM2P5": 35.05,
      "VOC": 116.98,
      "NH3": 96.28,
      "BC": 7.99,
      "key": "경상남도_비산업 연소"
  },
  {
      "sido": "경상남도",
      "source_main": "제조업 연소",
      "CO": 545.05,
      "NOx": 1925.77,
      "SOx": 389.06,
      "TSP": 133.25,
      "PM10": 83.72,
      "PM2P5": 48.62,
      "VOC": 78.15,
      "NH3": 26.85,
      "BC": 4.74,
      "key": "경상남도_제조업 연소"
  },
  {
      "sido": "경상남도",
      "source_main": "생산공정",
      "CO": 0,
      "NOx": 386.11,
      "SOx": 675.64,
      "TSP": 30.13,
      "PM10": 21.76,
      "PM2P5": 15.75,
      "VOC": 5444.17,
      "NH3": 1956.27,
      "BC": 0.06,
      "key": "경상남도_생산공정"
  },
  {
      "sido": "경상남도",
      "source_main": "에너지수송 및 저장",
      "CO": 0,
      "NOx": 0,
      "SOx": 0,
      "TSP": 0,
      "PM10": 0,
      "PM2P5": 0,
      "VOC": 857.99,
      "NH3": 0,
      "BC": 0,
      "key": "경상남도_에너지수송 및 저장"
  },
  {
      "sido": "경상남도",
      "source_main": "유기용제 사용",
      "CO": 0,
      "NOx": 0,
      "SOx": 0,
      "TSP": 0,
      "PM10": 0,
      "PM2P5": 0,
      "VOC": 25841.18,
      "NH3": 0,
      "BC": 0,
      "key": "경상남도_유기용제 사용"
  },
  {
      "sido": "경상남도",
      "source_main": "도로이동오염원",
      "CO": 7218.67,
      "NOx": 15364.98,
      "SOx": 11.72,
      "TSP": 213.04,
      "PM10": 213.04,
      "PM2P5": 196,
      "VOC": 1284.33,
      "NH3": 100.29,
      "BC": 117.25,
      "key": "경상남도_도로이동오염원"
  },
  {
      "sido": "경상남도",
      "source_main": "비도로이동오염원",
      "CO": 2059.57,
      "NOx": 6227.64,
      "SOx": 437.47,
      "TSP": 362.49,
      "PM10": 362.49,
      "PM2P5": 331.92,
      "VOC": 600.88,
      "NH3": 3.84,
      "BC": 174.35,
      "key": "경상남도_비도로이동오염원"
  },
  {
      "sido": "경상남도",
      "source_main": "폐기물처리",
      "CO": 75.72,
      "NOx": 253.72,
      "SOx": 64.44,
      "TSP": 11.9,
      "PM10": 8.61,
      "PM2P5": 7.06,
      "VOC": 1710.46,
      "NH3": 0.92,
      "BC": 0.11,
      "key": "경상남도_폐기물처리"
  },
  {
      "sido": "경상남도",
      "source_main": "농업",
      "CO": 0,
      "NOx": 0,
      "SOx": 0,
      "TSP": 0,
      "PM10": 0,
      "PM2P5": 0,
      "VOC": 0,
      "NH3": 7336.1,
      "BC": 0,
      "key": "경상남도_농업"
  },
  {
      "sido": "경상남도",
      "source_main": "기타 면오염원",
      "CO": 251.1,
      "NOx": 5.93,
      "SOx": 0,
      "TSP": 16.49,
      "PM10": 10.48,
      "PM2P5": 9.43,
      "VOC": 21.2,
      "NH3": 593.89,
      "BC": 0.43,
      "key": "경상남도_기타 면오염원"
  },
  {
      "sido": "경상남도",
      "source_main": "비산먼지",
      "CO": 0,
      "NOx": 0,
      "SOx": 0,
      "TSP": 12161.94,
      "PM10": 3407.26,
      "PM2P5": 617.33,
      "VOC": 0,
      "NH3": 0,
      "BC": 4.95,
      "key": "경상남도_비산먼지"
  },
  {
      "sido": "경상남도",
      "source_main": "생물성 연소",
      "CO": 7069.36,
      "NOx": 217.84,
      "SOx": 3.11,
      "TSP": 836.2,
      "PM10": 417.75,
      "PM2P5": 346.31,
      "VOC": 1778.85,
      "NH3": 0.5,
      "BC": 53.99,
      "key": "경상남도_생물성 연소"
  },
  {
      "sido": "경상남도",
      "source_main": "에너지산업 연소",
      "CO": 3300.35,
      "NOx": 7076.79,
      "SOx": 5243.9,
      "TSP": 392.61,
      "PM10": 383.49,
      "PM2P5": 309.37,
      "VOC": 398.89,
      "NH3": 13.22,
      "BC": 6.54,
      "key": "경상남도_에너지산업 연소"
  }
]